spaceone/__init__.py
spaceone/board/__init__.py
spaceone/board/conf/__init__.py
spaceone/board/conf/board_conf.py
spaceone/board/conf/global_conf.py
spaceone/board/conf/proto_conf.py
spaceone/board/connector/__init__.py
spaceone/board/error/__init__.py
spaceone/board/error/board.py
spaceone/board/error/post.py
spaceone/board/info/__init__.py
spaceone/board/info/board_info.py
spaceone/board/info/common_info.py
spaceone/board/info/post_info.py
spaceone/board/interface/__init__.py
spaceone/board/interface/grpc/__init__.py
spaceone/board/interface/grpc/v1/__init__.py
spaceone/board/interface/grpc/v1/board.py
spaceone/board/interface/grpc/v1/post.py
spaceone/board/lib/__init__.py
spaceone/board/manager/__init__.py
spaceone/board/manager/board_manager.py
spaceone/board/manager/file_manager.py
spaceone/board/manager/identity_manager.py
spaceone/board/manager/post_manager.py
spaceone/board/model/__init__.py
spaceone/board/model/board_model.py
spaceone/board/model/post_model.py
spaceone/board/service/__init__.py
spaceone/board/service/board_service.py
spaceone/board/service/post_service.py
spaceone_board-1.12.0.dist-info/METADATA
spaceone_board-1.12.0.dist-info/WHEEL
spaceone_board-1.12.0.dist-info/top_level.txt
spaceone_board-1.12.0.dist-info/RECORD
